pip_validate.py
pip_validate-1.2.0.dist-info/LICENSE
pip_validate-1.2.0.dist-info/METADATA
pip_validate-1.2.0.dist-info/WHEEL
pip_validate-1.2.0.dist-info/entry_points.txt
pip_validate-1.2.0.dist-info/top_level.txt
pip_validate-1.2.0.dist-info/RECORD
