Metadata-Version: 2.1
Name: pip-validate
Version: 1.2.0
Summary: Validate toplevel imports against requirements.txt
Home-page: https://github.com/ohjeah/pip-validate
Author: Markus Quade
Author-email: info@markusqua.de
License: MIT
Platform: UNKNOWN
Classifier: Programming Language :: Python
Classifier: Programming Language :: Python :: 3.5
Classifier: Programming Language :: Python :: 3.6
Requires-Dist: pip (>=20)
Requires-Dist: crayons
